LICENSE
MANIFEST.in
README.rst
setup.py
datacash/__init__.py
datacash/admin.py
datacash/facade.py
datacash/gateway.py
datacash/models.py
datacash/urls.py
datacash/xmlutils.py
datacash/dashboard/__init__.py
datacash/dashboard/app.py
datacash/dashboard/views.py
datacash/migrations/0001_initial.py
datacash/migrations/0002_auto__add_fraudresponse.py
datacash/migrations/0003_auto__del_unique_fraudresponse_t3m_id.py
datacash/migrations/0004_auto__add_field_ordertransaction_currency.py
datacash/migrations/__init__.py
datacash/templates/datacash/dashboard/fraudresponse_list.html
datacash/templates/datacash/dashboard/transaction_detail.html
datacash/templates/datacash/dashboard/transaction_list.html
datacash/the3rdman/__init__.py
datacash/the3rdman/document.py
datacash/the3rdman/signals.py
datacash/the3rdman/utils.py
datacash/the3rdman/views.py
django_oscar_datacash.egg-info/PKG-INFO
django_oscar_datacash.egg-info/SOURCES.txt
django_oscar_datacash.egg-info/dependency_links.txt
django_oscar_datacash.egg-info/requires.txt
django_oscar_datacash.egg-info/top_level.txt