Metadata-Version: 1.0
Name: django-oscar-datacash
Version: 0.6.3
Summary: Datacash payment module for django-oscar
Home-page: https://github.com/tangentlabs/django-oscar-datacash
Author: David Winterbottom
Author-email: david.winterbottom@tangentlabs.co.uk
License: BSD
Keywords: Payment,Datacash
Platform: UNKNOWN
Classifier: Environment :: Web Environment
Classifier: Framework :: Django
Classifier: Intended Audience :: Developers
Classifier: License :: OSI Approved :: BSD License
Classifier: Operating System :: Unix
Classifier: Programming Language :: Python
